{
  "asset": {
    "version": "1.0"
  },
  "geometricError": 100.0,
  "root": {
    "transform": [
      -0.15971367836948433,
      0.9871633810781724,
      0.0,
      0.0,
      -0.6923512462307532,
      -0.11201586928643742,
      -0.7128128764765173,
      0.0,
      -0.7036627692186164,
      -0.11384596649119744,
      0.7013542636423288,
      0.0,
      4423440.518572955,
      715670.7489476459,
      4523682.777249485,
      1.0
    ],
    "boundingVolume": {
      "box": [
        2.0813235,
        0.20404650000000046,
        6.089029,
        23.6545295,
        0.0,
        0.0,
        0.0,
        -16.4759865,
        0.0,
        0.0,
        0.0,
        5.820066000000001
      ]
    },
    "geometricError": 100.0,
    "refine": "ADD",
    "content": null,
    "children": [
      {
        "transform": null,
        "boundingVolume": {
          "box": [
            3.605485553511035,
            0.8124395650534089,
            10.454078500000001,
            1.5241620535110352,
            0.0,
            0.0,
            0.0,
            -12.190232649202859,
            0.0,
            0.0,
            0.0,
            1.4550165000000002
          ]
        },
        "geometricError": 9.004003538900639,
        "refine": "REPLACE",
        "content": {
          "uri": "LOD-2/Mesh-XR-YR-XL-YR.b3dm"
        },
        "children": [
          {
            "transform": null,
            "boundingVolume": {
              "box": [
                3.605485553511035,
                0.817593593981127,
                10.454078500000001,
                1.5241620535110352,
                0.0,
                0.0,
                0.0,
                -12.194702406018873,
                0.0,
                0.0,
                0.0,
                1.4550165000000002
              ]
            },
            "geometricError": 3.0003005111235796,
            "refine": "REPLACE",
            "content": {
              "uri": "LOD-1/Mesh-XR-YR-XL-YR.b3dm"
            },
            "children": [
              {
                "transform": null,
                "boundingVolume": {
                  "box": [
                    3.6059265088831736,
                    0.8174569999999992,
                    10.454078500000001,
                    1.5246030088831737,
                    0.0,
                    0.0,
                    0.0,
                    -12.194839,
                    0.0,
                    0.0,
                    0.0,
                    1.4550165000000002
                  ]
                },
                "geometricError": 0.0,
                "refine": "REPLACE",
                "content": {
                  "uri": "LOD-0/Mesh-XR-YR-XL-YR.b3dm"
                },
                "children": []
              }
            ]
          }
        ]
      },
      {
        "transform": null,
        "boundingVolume": {
          "box": [
            5.8437004497452865,
            0.8289967490378132,
            7.5440455,
            3.7623769497452866,
            0.0,
            0.0,
            0.0,
            -12.169860447830406,
            0.0,
            0.0,
            0.0,
            1.4550165000000002
          ]
        },
        "geometricError": 9.001472394015456,
        "refine": "REPLACE",
        "content": {
          "uri": "LOD-2/Mesh-XR-YR-XL-YL.b3dm"
        },
        "children": [
          {
            "transform": null,
            "boundingVolume": {
              "box": [
                5.84281875,
                0.8296986498758248,
                7.5440455,
                3.7614952500000003,
                0.0,
                0.0,
                0.0,
                -12.169589017146329,
                0.0,
                0.0,
                0.0,
                1.4550165000000002
              ]
            },
            "geometricError": 3.0000333467600404,
            "refine": "REPLACE",
            "content": {
              "uri": "LOD-1/Mesh-XR-YR-XL-YL.b3dm"
            },
            "children": [
              {
                "transform": null,
                "boundingVolume": {
                  "box": [
                    5.84281875,
                    0.8292928335110767,
                    7.5440455,
                    3.7614952500000003,
                    0.0,
                    0.0,
                    0.0,
                    -12.169994833511076,
                    0.0,
                    0.0,
                    0.0,
                    1.4550165000000002
                  ]
                },
                "geometricError": 0.0,
                "refine": "REPLACE",
                "content": {
                  "uri": "LOD-0/Mesh-XR-YR-XL-YL.b3dm"
                },
                "children": []
              }
            ]
          }
        ]
      },
      {
        "transform": null,
        "boundingVolume": {
          "box": [
            -3.6889845611184695,
            0.8080877291676112,
            10.453922882618711,
            5.770308061118469,
            0.0,
            0.0,
            0.0,
            -12.180461686295704,
            0.0,
            0.0,
            0.0,
            1.4548608826187106
          ]
        },
        "geometricError": 9.049554146712694,
        "refine": "REPLACE",
        "content": {
          "uri": "LOD-2/Mesh-XL-YR-XR-YR.b3dm"
        },
        "children": [
          {
            "transform": null,
            "boundingVolume": {
              "box": [
                -3.7182250974499462,
                0.8082700716888169,
                10.454012556536636,
                5.799548597449946,
                0.0,
                0.0,
                0.0,
                -12.183591928311182,
                0.0,
                0.0,
                0.0,
                1.4549505565366365
              ]
            },
            "geometricError": 3.0029127061018834,
            "refine": "REPLACE",
            "content": {
              "uri": "LOD-1/Mesh-XL-YR-XR-YR.b3dm"
            },
            "children": [
              {
                "transform": null,
                "boundingVolume": {
                  "box": [
                    -3.7349271258542087,
                    0.8086699602818461,
                    10.454012556536636,
                    5.816250625854209,
                    0.0,
                    0.0,
                    0.0,
                    -12.183192039718154,
                    0.0,
                    0.0,
                    0.0,
                    1.4549505565366365
                  ]
                },
                "geometricError": 0.0,
                "refine": "REPLACE",
                "content": {
                  "uri": "LOD-0/Mesh-XL-YR-XR-YR.b3dm"
                },
                "children": []
              }
            ]
          }
        ]
      },
      {
        "transform": null,
        "boundingVolume": {
          "box": [
            -11.04605873040422,
            -6.637299996185664,
            9.006376,
            1.1489258845320824,
            0.0,
            0.0,
            0.0,
            -0.02911314437993795,
            0.0,
            0.0,
            0.0,
            0.007314000000000043
          ]
        },
        "geometricError": 9.715545680506663,
        "refine": "REPLACE",
        "content": {
          "uri": "LOD-2/Mesh-XL-YR-XL-YR.b3dm"
        },
        "children": [
          {
            "transform": null,
            "boundingVolume": {
              "box": [
                -11.084880772822595,
                -6.642153146075101,
                9.006376,
                1.117380253197668,
                0.0,
                0.0,
                0.0,
                -0.023477200999785452,
                0.0,
                0.0,
                0.0,
                0.007314000000000043
              ]
            },
            "geometricError": 3.1281499040509964,
            "refine": "REPLACE",
            "content": {
              "uri": "LOD-1/Mesh-XL-YR-XL-YR.b3dm"
            },
            "children": [
              {
                "transform": null,
                "boundingVolume": {
                  "box": [
                    -11.077661528140613,
                    -6.644738877547892,
                    9.006376,
                    1.122260113820139,
                    0.0,
                    0.0,
                    0.0,
                    -0.026383271633481975,
                    0.0,
                    0.0,
                    0.0,
                    0.007314000000000043
                  ]
                },
                "geometricError": 0.0,
                "refine": "REPLACE",
                "content": {
                  "uri": "LOD-0/Mesh-XL-YR-XL-YR.b3dm"
                },
                "children": []
              }
            ]
          }
        ]
      },
      {
        "transform": null,
        "boundingVolume": {
          "box": [
            -3.832308875,
            0.729732508577138,
            7.5440455,
            5.913632375,
            0.0,
            0.0,
            0.0,
            -12.349704096883114,
            0.0,
            0.0,
            0.0,
            1.4550165000000002
          ]
        },
        "geometricError": 9.002317566541363,
        "refine": "REPLACE",
        "content": {
          "uri": "LOD-2/Mesh-XL-YR-XR-YL.b3dm"
        },
        "children": [
          {
            "transform": null,
            "boundingVolume": {
              "box": [
                -3.832308875,
                0.7346725000000003,
                7.5440455,
                5.913632375,
                0.0,
                0.0,
                0.0,
                -12.3538345,
                0.0,
                0.0,
                0.0,
                1.4550165000000002
              ]
            },
            "geometricError": 3.000051765304125,
            "refine": "REPLACE",
            "content": {
              "uri": "LOD-1/Mesh-XL-YR-XR-YL.b3dm"
            },
            "children": [
              {
                "transform": null,
                "boundingVolume": {
                  "box": [
                    -3.832308875,
                    0.7340330000000002,
                    7.5440455,
                    5.913632375,
                    0.0,
                    0.0,
                    0.0,
                    -12.354474,
                    0.0,
                    0.0,
                    0.0,
                    1.4550165000000002
                  ]
                },
                "geometricError": 0.0,
                "refine": "REPLACE",
                "content": {
                  "uri": "LOD-0/Mesh-XL-YR-XR-YL.b3dm"
                },
                "children": []
              }
            ]
          }
        ]
      },
      {
        "transform": null,
        "boundingVolume": {
          "box": [
            -10.987848125,
            -6.585320278973358,
            7.5440455,
            1.2419068750000006,
            0.0,
            0.0,
            0.0,
            -3.6394490861085456,
            0.0,
            0.0,
            0.0,
            1.4550165000000002
          ]
        },
        "geometricError": 9.003342822298958,
        "refine": "REPLACE",
        "content": {
          "uri": "LOD-2/Mesh-XL-YR-XL-YL.b3dm"
        },
        "children": [
          {
            "transform": null,
            "boundingVolume": {
              "box": [
                -10.987848125,
                -6.585080724586665,
                7.5440455,
                1.2419068750000006,
                0.0,
                0.0,
                0.0,
                -3.6396732213797174,
                0.0,
                0.0,
                0.0,
                1.4550165000000002
              ]
            },
            "geometricError": 3.000495469867504,
            "refine": "REPLACE",
            "content": {
              "uri": "LOD-1/Mesh-XL-YR-XL-YL.b3dm"
            },
            "children": [
              {
                "transform": null,
                "boundingVolume": {
                  "box": [
                    -10.987848125,
                    -6.587117734497518,
                    7.5440455,
                    1.2419068750000006,
                    0.0,
                    0.0,
                    0.0,
                    -3.6414765697884715,
                    0.0,
                    0.0,
                    0.0,
                    1.4550165000000002
                  ]
                },
                "geometricError": 0.0,
                "refine": "REPLACE",
                "content": {
                  "uri": "LOD-0/Mesh-XL-YR-XL-YL.b3dm"
                },
                "children": []
              }
            ]
          }
        ]
      },
      {
        "transform": null,
        "boundingVolume": {
          "box": [
            19.684634043850604,
            4.278381494825263,
            3.8667829937156353,
            5.776045793850606,
            0.0,
            0.0,
            0.0,
            -8.746432920353607,
            0.0,
            0.0,
            0.0,
            0.6877869937156347
          ]
        },
        "geometricError": 9.04923568424565,
        "refine": "REPLACE",
        "content": {
          "uri": "LOD-2/Mesh-XR-YL-XR-YR.b3dm"
        },
        "children": [
          {
            "transform": null,
            "boundingVolume": {
              "box": [
                19.684634043850604,
                4.283136444964848,
                3.8718845,
                5.776045793850606,
                0.0,
                0.0,
                0.0,
                -8.749542093790609,
                0.0,
                0.0,
                0.0,
                0.6928884999999996
              ]
            },
            "geometricError": 3.0004218495874038,
            "refine": "REPLACE",
            "content": {
              "uri": "LOD-1/Mesh-XR-YL-XR-YR.b3dm"
            },
            "children": [
              {
                "transform": null,
                "boundingVolume": {
                  "box": [
                    19.684634043850604,
                    4.27944545424261,
                    3.8718845,
                    5.776045793850606,
                    0.0,
                    0.0,
                    0.0,
                    -8.753233084512846,
                    0.0,
                    0.0,
                    0.0,
                    0.6928884999999996
                  ]
                },
                "geometricError": 0.0,
                "refine": "REPLACE",
                "content": {
                  "uri": "LOD-0/Mesh-XR-YL-XR-YR.b3dm"
                },
                "children": []
              }
            ]
          }
        ]
      },
      {
        "transform": null,
        "boundingVolume": {
          "box": [
            7.994955875,
            0.8443588692895254,
            4.634012500000001,
            5.913632375,
            0.0,
            0.0,
            0.0,
            -12.122079130710475,
            0.0,
            0.0,
            0.0,
            1.4550164999999997
          ]
        },
        "geometricError": 9.000185547982777,
        "refine": "REPLACE",
        "content": {
          "uri": "LOD-2/Mesh-XR-YL-XL-YR.b3dm"
        },
        "children": [
          {
            "transform": null,
            "boundingVolume": {
              "box": [
                7.994955875,
                0.8452489999999999,
                4.634012500000001,
                5.913632375,
                0.0,
                0.0,
                0.0,
                -12.121945,
                0.0,
                0.0,
                0.0,
                1.4550164999999997
              ]
            },
            "geometricError": 3.000041989961182,
            "refine": "REPLACE",
            "content": {
              "uri": "LOD-1/Mesh-XR-YL-XL-YR.b3dm"
            },
            "children": [
              {
                "transform": null,
                "boundingVolume": {
                  "box": [
                    7.994955875,
                    0.8447399999999998,
                    4.634012500000001,
                    5.913632375,
                    0.0,
                    0.0,
                    0.0,
                    -12.122454,
                    0.0,
                    0.0,
                    0.0,
                    1.4550164999999997
                  ]
                },
                "geometricError": 0.0,
                "refine": "REPLACE",
                "content": {
                  "uri": "LOD-0/Mesh-XR-YL-XL-YR.b3dm"
                },
                "children": []
              }
            ]
          }
        ]
      },
      {
        "transform": null,
        "boundingVolume": {
          "box": [
            19.822220625,
            1.336804645461548,
            1.7239800000000003,
            5.913632375,
            0.0,
            0.0,
            0.0,
            -15.071423354538453,
            0.0,
            0.0,
            0.0,
            1.4550160000000003
          ]
        },
        "geometricError": 9.0,
        "refine": "REPLACE",
        "content": {
          "uri": "LOD-2/Mesh-XR-YL-XR-YL.b3dm"
        },
        "children": [
          {
            "transform": null,
            "boundingVolume": {
              "box": [
                19.822220625,
                1.336804645461548,
                1.7239800000000003,
                5.913632375,
                0.0,
                0.0,
                0.0,
                -15.071423354538453,
                0.0,
                0.0,
                0.0,
                1.4550160000000003
              ]
            },
            "geometricError": 3.0,
            "refine": "REPLACE",
            "content": {
              "uri": "LOD-1/Mesh-XR-YL-XR-YL.b3dm"
            },
            "children": [
              {
                "transform": null,
                "boundingVolume": {
                  "box": [
                    19.822220625,
                    1.336804645461548,
                    1.7239800000000003,
                    5.913632375,
                    0.0,
                    0.0,
                    0.0,
                    -15.071423354538453,
                    0.0,
                    0.0,
                    0.0,
                    1.4550160000000003
                  ]
                },
                "geometricError": 0.0,
                "refine": "REPLACE",
                "content": {
                  "uri": "LOD-0/Mesh-XR-YL-XR-YL.b3dm"
                },
                "children": []
              }
            ]
          }
        ]
      },
      {
        "transform": null,
        "boundingVolume": {
          "box": [
            7.994955875,
            0.28317901912770616,
            1.7239795000000002,
            5.913632375,
            0.0,
            0.0,
            0.0,
            -16.396853980872294,
            0.0,
            0.0,
            0.0,
            1.4550165000000004
          ]
        },
        "geometricError": 9.0,
        "refine": "REPLACE",
        "content": {
          "uri": "LOD-2/Mesh-XR-YL-XL-YL.b3dm"
        },
        "children": [
          {
            "transform": null,
            "boundingVolume": {
              "box": [
                7.994955875,
                0.28317901912770616,
                1.7239795000000002,
                5.913632375,
                0.0,
                0.0,
                0.0,
                -16.396853980872294,
                0.0,
                0.0,
                0.0,
                1.4550165000000004
              ]
            },
            "geometricError": 3.0,
            "refine": "REPLACE",
            "content": {
              "uri": "LOD-1/Mesh-XR-YL-XL-YL.b3dm"
            },
            "children": [
              {
                "transform": null,
                "boundingVolume": {
                  "box": [
                    7.994955875,
                    0.28317901912770616,
                    1.7239795000000002,
                    5.913632375,
                    0.0,
                    0.0,
                    0.0,
                    -16.396853980872294,
                    0.0,
                    0.0,
                    0.0,
                    1.4550165000000004
                  ]
                },
                "geometricError": 0.0,
                "refine": "REPLACE",
                "content": {
                  "uri": "LOD-0/Mesh-XR-YL-XL-YL.b3dm"
                },
                "children": []
              }
            ]
          }
        ]
      },
      {
        "transform": null,
        "boundingVolume": {
          "box": [
            -3.832308875,
            0.7667641663468485,
            4.634012500000001,
            5.913632375,
            0.0,
            0.0,
            0.0,
            -12.39960231595802,
            0.0,
            0.0,
            0.0,
            1.4550164999999997
          ]
        },
        "geometricError": 9.000355571024125,
        "refine": "REPLACE",
        "content": {
          "uri": "LOD-2/Mesh-XL-YL-XR-YR.b3dm"
        },
        "children": [
          {
            "transform": null,
            "boundingVolume": {
              "box": [
                -3.832308875,
                0.7651924999999995,
                4.634012500000001,
                5.913632375,
                0.0,
                0.0,
                0.0,
                -12.3988675,
                0.0,
                0.0,
                0.0,
                1.4550164999999997
              ]
            },
            "geometricError": 3.0,
            "refine": "REPLACE",
            "content": {
              "uri": "LOD-1/Mesh-XL-YL-XR-YR.b3dm"
            },
            "children": [
              {
                "transform": null,
                "boundingVolume": {
                  "box": [
                    -3.832308875,
                    0.7651924999999995,
                    4.634012500000001,
                    5.913632375,
                    0.0,
                    0.0,
                    0.0,
                    -12.3988675,
                    0.0,
                    0.0,
                    0.0,
                    1.4550164999999997
                  ]
                },
                "geometricError": 0.0,
                "refine": "REPLACE",
                "content": {
                  "uri": "LOD-0/Mesh-XL-YL-XR-YR.b3dm"
                },
                "children": []
              }
            ]
          }
        ]
      },
      {
        "transform": null,
        "boundingVolume": {
          "box": [
            -11.202512619021636,
            0.7817669224699388,
            4.634012500000001,
            1.4565713690216366,
            0.0,
            0.0,
            0.0,
            -12.287666922469938,
            0.0,
            0.0,
            0.0,
            1.4550164999999997
          ]
        },
        "geometricError": 9.00745283864569,
        "refine": "REPLACE",
        "content": {
          "uri": "LOD-2/Mesh-XL-YL-XL-YR.b3dm"
        },
        "children": [
          {
            "transform": null,
            "boundingVolume": {
              "box": [
                -11.200802125,
                0.7808548034587028,
                4.634012500000001,
                1.4548608750000005,
                0.0,
                0.0,
                0.0,
                -12.286754803458702,
                0.0,
                0.0,
                0.0,
                1.4550164999999997
              ]
            },
            "geometricError": 3.0001417946861615,
            "refine": "REPLACE",
            "content": {
              "uri": "LOD-1/Mesh-XL-YL-XL-YR.b3dm"
            },
            "children": [
              {
                "transform": null,
                "boundingVolume": {
                  "box": [
                    -11.200802125,
                    0.7811789999999998,
                    4.634012500000001,
                    1.4548608750000005,
                    0.0,
                    0.0,
                    0.0,
                    -12.288497,
                    0.0,
                    0.0,
                    0.0,
                    1.4550164999999997
                  ]
                },
                "geometricError": 0.0,
                "refine": "REPLACE",
                "content": {
                  "uri": "LOD-0/Mesh-XL-YL-XL-YR.b3dm"
                },
                "children": []
              }
            ]
          }
        ]
      },
      {
        "transform": null,
        "boundingVolume": {
          "box": [
            -3.832308875,
            0.15054250000000025,
            1.7239800000000003,
            5.913632375,
            0.0,
            0.0,
            0.0,
            -16.4224825,
            0.0,
            0.0,
            0.0,
            1.4550160000000003
          ]
        },
        "geometricError": 9.0,
        "refine": "REPLACE",
        "content": {
          "uri": "LOD-2/Mesh-XL-YL-XR-YL.b3dm"
        },
        "children": [
          {
            "transform": null,
            "boundingVolume": {
              "box": [
                -3.832308875,
                0.15054250000000025,
                1.7239800000000003,
                5.913632375,
                0.0,
                0.0,
                0.0,
                -16.4224825,
                0.0,
                0.0,
                0.0,
                1.4550160000000003
              ]
            },
            "geometricError": 3.0,
            "refine": "REPLACE",
            "content": {
              "uri": "LOD-1/Mesh-XL-YL-XR-YL.b3dm"
            },
            "children": [
              {
                "transform": null,
                "boundingVolume": {
                  "box": [
                    -3.832308875,
                    0.15054250000000025,
                    1.7239800000000003,
                    5.913632375,
                    0.0,
                    0.0,
                    0.0,
                    -16.4224825,
                    0.0,
                    0.0,
                    0.0,
                    1.4550160000000003
                  ]
                },
                "geometricError": 0.0,
                "refine": "REPLACE",
                "content": {
                  "uri": "LOD-0/Mesh-XL-YL-XR-YL.b3dm"
                },
                "children": []
              }
            ]
          }
        ]
      },
      {
        "transform": null,
        "boundingVolume": {
          "box": [
            -15.659573625,
            0.2755719999999995,
            1.7239800000000003,
            5.913632375,
            0.0,
            0.0,
            0.0,
            -16.15983,
            0.0,
            0.0,
            0.0,
            1.4550160000000003
          ]
        },
        "geometricError": 9.0,
        "refine": "REPLACE",
        "content": {
          "uri": "LOD-2/Mesh-XL-YL-XL-YL.b3dm"
        },
        "children": [
          {
            "transform": null,
            "boundingVolume": {
              "box": [
                -15.659573625,
                0.2755719999999995,
                1.7239800000000003,
                5.913632375,
                0.0,
                0.0,
                0.0,
                -16.15983,
                0.0,
                0.0,
                0.0,
                1.4550160000000003
              ]
            },
            "geometricError": 3.0,
            "refine": "REPLACE",
            "content": {
              "uri": "LOD-1/Mesh-XL-YL-XL-YL.b3dm"
            },
            "children": [
              {
                "transform": null,
                "boundingVolume": {
                  "box": [
                    -15.659573625,
                    0.2755719999999995,
                    1.7239800000000003,
                    5.913632375,
                    0.0,
                    0.0,
                    0.0,
                    -16.15983,
                    0.0,
                    0.0,
                    0.0,
                    1.4550160000000003
                  ]
                },
                "geometricError": 0.0,
                "refine": "REPLACE",
                "content": {
                  "uri": "LOD-0/Mesh-XL-YL-XL-YL.b3dm"
                },
                "children": []
              }
            ]
          }
        ]
      }
    ]
  }
}